show_details/__init__.py
show_details/show_items.py
claimSurs-0.0.1.dist-info/METADATA
claimSurs-0.0.1.dist-info/WHEEL
claimSurs-0.0.1.dist-info/top_level.txt
claimSurs-0.0.1.dist-info/RECORD
