Metadata-Version: 2.1
Name: claimSurs
Version: 0.0.1
Summary: package test that can print kwargs class with modul
Home-page: https://pypi.org/user/Yato_uid/
Author: Yato_kun
